{
    "fluentMethods": true,
    "relationships": [
        {
            "relationshipName": "ba10Menu",
            "otherEntityName": "ba10Menu",
            "relationshipType": "many-to-one",
            "otherEntityField": "id"
        },
        {
            "relationshipType": "one-to-many",
            "relationshipName": "childs",
            "otherEntityName": "ba10Menu",
            "otherEntityRelationshipName": "ba10Menu"
        },
        {
            "relationshipType": "many-to-one",
            "relationshipName": "menuParent",
            "otherEntityName": "ba10Menu",
            "otherEntityField": "id"
        }
    ],
    "fields": [
        {
            "fieldName": "nmNome",
            "fieldType": "String",
            "fieldValidateRules": [
                "maxlength"
            ],
            "fieldValidateRulesMaxlength": 100
        },
        {
            "fieldName": "cdCod",
            "fieldType": "String",
            "fieldValidateRules": [
                "required",
                "maxlength"
            ],
            "fieldValidateRulesMaxlength": 100
        },
        {
            "fieldName": "dbOrdine",
            "fieldType": "String",
            "fieldValidateRules": [
                "maxlength"
            ],
            "fieldValidateRulesMaxlength": 100
        },
        {
            "fieldName": "dlPath",
            "fieldType": "String",
            "fieldValidateRules": [
                "maxlength"
            ],
            "fieldValidateRulesMaxlength": 400
        },
        {
            "fieldName": "dlIcon",
            "fieldType": "String",
            "fieldValidateRules": [
                "maxlength"
            ],
            "fieldValidateRulesMaxlength": 400
        },
        {
            "fieldName": "blLink",
            "fieldType": "Boolean"
        }
    ],
    "changelogDate": "20180109113122",
    "entityTableName": "ba_10_menu",
    "dto": "no",
    "pagination": "no",
    "service": "no",
    "jpaMetamodelFiltering": false
}