{
    "fluentMethods": true,
    "relationships": [
        {
            "relationshipType": "one-to-one",
            "relationshipName": "widgetImpl",
            "otherEntityName": "widgetImpl",
            "otherEntityField": "id",
            "ownerSide": true,
            "otherEntityRelationshipName": "tipiWidget"
        }
    ],
    "fields": [
        {
            "fieldName": "dbTipo",
            "fieldType": "String",
            "fieldValidateRules": [
                "maxlength"
            ],
            "fieldValidateRulesMaxlength": 100
        },
        {
            "fieldName": "dbTipoCont",
            "fieldType": "String",
            "fieldValidateRules": [
                "maxlength"
            ],
            "fieldValidateRulesMaxlength": 100
        },
        {
            "fieldName": "flDrill",
            "fieldType": "Boolean"
        }
    ],
    "changelogDate": "20180109114400",
    "entityTableName": "tipi_widget",
    "dto": "no",
    "pagination": "no",
    "service": "no",
    "jpaMetamodelFiltering": false
}